{
    "file_name": "KS-FR-LEMANS/24652/camcourt1_1513023903804_0.png",
    "predictions": [
        {
            "category_id": 0,
            "bbox": [
                2136.743408203125,
                863.2111206054688,
                2198.810302734375,
                917.4892578125
            ],
            "score": 0.8163192272186279
        },
        {
            "category_id": 0,
            "bbox": [
                1319.19580078125,
                863.6423950195312,
                1400.9154052734375,
                1095.7769775390625
            ],
            "score": 0.8148942589759827
        },
        {
            "category_id": 0,
            "bbox": [
                2036.564208984375,
                1453.8536376953125,
                2090.266845703125,
                1507.437255859375
            ],
            "score": 0.8089181184768677
        },
        {
            "category_id": 0,
            "bbox": [
                1386.416748046875,
                887.7621459960938,
                1470.6781005859375,
                1107.2861328125
            ],
            "score": 0.807019829750061
        },
        {
            "category_id": 0,
            "bbox": [
                2148.982421875,
                1026.309814453125,
                2207.970947265625,
                1106.6517333984375
            ],
            "score": 0.804664671421051
        },
        {
            "category_id": 0,
            "bbox": [
                1324.6134033203125,
                836.6265258789062,
                1468.91748046875,
                981.4547119140625
            ],
            "score": 0.8042842745780945
        },
        {
            "category_id": 0,
            "bbox": [
                1521.7874755859375,
                1554.3216552734375,
                1581.0703125,
                1622.9925537109375
            ],
            "score": 0.8027878403663635
        },
        {
            "category_id": 0,
            "bbox": [
                1661.1417236328125,
                1373.956787109375,
                1709.9892578125,
                1451.323486328125
            ],
            "score": 0.8016565442085266
        },
        {
            "category_id": 0,
            "bbox": [
                527.767822265625,
                724.26025390625,
                668.821533203125,
                892.1226196289062
            ],
            "score": 0.7987838387489319
        },
        {
            "category_id": 0,
            "bbox": [
                605.129638671875,
                359.3336181640625,
                676.9757690429688,
                439.1853942871094
            ],
            "score": 0.7963905930519104
        },
        {
            "category_id": 0,
            "bbox": [
                787.8037719726562,
                1585.5628662109375,
                835.040283203125,
                1673.1484375
            ],
            "score": 0.7963869571685791
        },
        {
            "category_id": 0,
            "bbox": [
                1632.697998046875,
                1373.7637939453125,
                1687.219482421875,
                1453.9139404296875
            ],
            "score": 0.7934832572937012
        },
        {
            "category_id": 0,
            "bbox": [
                645.5625610351562,
                743.69873046875,
                783.7255249023438,
                911.836669921875
            ],
            "score": 0.793212890625
        },
        {
            "category_id": 0,
            "bbox": [
                2024.48974609375,
                1012.9246826171875,
                2225.65771484375,
                1511.493408203125
            ],
            "score": 0.7922590970993042
        },
        {
            "category_id": 0,
            "bbox": [
                1690.9483642578125,
                1381.6759033203125,
                1746.8416748046875,
                1471.5257568359375
            ],
            "score": 0.784824013710022
        },
        {
            "category_id": 0,
            "bbox": [
                2081.972412109375,
                1193.289794921875,
                2209.21923828125,
                1359.3125
            ],
            "score": 0.780098557472229
        },
        {
            "category_id": 0,
            "bbox": [
                1427.305908203125,
                820.4891357421875,
                1498.6300048828125,
                1051.9178466796875
            ],
            "score": 0.7759990096092224
        },
        {
            "category_id": 0,
            "bbox": [
                1436.8642578125,
                843.2100830078125,
                1507.9573974609375,
                904.0999755859375
            ],
            "score": 0.7745144963264465
        },
        {
            "category_id": 0,
            "bbox": [
                735.3649291992188,
                623.1812133789062,
                854.6077880859375,
                815.8444213867188
            ],
            "score": 0.7706093788146973
        },
        {
            "category_id": 0,
            "bbox": [
                1980.9132080078125,
                1249.066162109375,
                2111.162109375,
                1410.3017578125
            ],
            "score": 0.7689807415008545
        },
        {
            "category_id": 0,
            "bbox": [
                566.4295654296875,
                265.3519287109375,
                665.7686767578125,
                409.8314514160156
            ],
            "score": 0.7674337029457092
        },
        {
            "category_id": 0,
            "bbox": [
                1200.625,
                793.6431274414062,
                1259.5975341796875,
                851.925537109375
            ],
            "score": 0.7670202255249023
        },
        {
            "category_id": 0,
            "bbox": [
                1935.138671875,
                1407.01171875,
                1985.1771240234375,
                1475.01123046875
            ],
            "score": 0.7648119330406189
        },
        {
            "category_id": 0,
            "bbox": [
                1313.5806884765625,
                822.6624755859375,
                1374.4263916015625,
                893.2307739257812
            ],
            "score": 0.7633395791053772
        },
        {
            "category_id": 0,
            "bbox": [
                1327.17431640625,
                801.4620971679688,
                1408.172607421875,
                1029.386474609375
            ],
            "score": 0.762660026550293
        },
        {
            "category_id": 0,
            "bbox": [
                1527.9913330078125,
                1538.12255859375,
                1590.5653076171875,
                1596.3441162109375
            ],
            "score": 0.7625938057899475
        },
        {
            "category_id": 0,
            "bbox": [
                1545.4139404296875,
                455.66497802734375,
                1608.4593505859375,
                533.0724487304688
            ],
            "score": 0.7621937990188599
        },
        {
            "category_id": 0,
            "bbox": [
                990.782958984375,
                1298.8106689453125,
                1057.302978515625,
                1376.9254150390625
            ],
            "score": 0.7620803713798523
        },
        {
            "category_id": 0,
            "bbox": [
                1189.985107421875,
                652.5234985351562,
                1320.920654296875,
                815.5689086914062
            ],
            "score": 0.7617425918579102
        },
        {
            "category_id": 0,
            "bbox": [
                459.44085693359375,
                754.586669921875,
                579.85546875,
                908.912841796875
            ],
            "score": 0.7590561509132385
        },
        {
            "category_id": 0,
            "bbox": [
                811.4031372070312,
                1591.3555908203125,
                866.32763671875,
                1686.9710693359375
            ],
            "score": 0.758968710899353
        },
        {
            "category_id": 0,
            "bbox": [
                1286.931396484375,
                792.6422729492188,
                1421.0550537109375,
                948.3867797851562
            ],
            "score": 0.7584452033042908
        },
        {
            "category_id": 0,
            "bbox": [
                270.02789306640625,
                1264.6759033203125,
                413.48748779296875,
                1414.0733642578125
            ],
            "score": 0.7577092051506042
        },
        {
            "category_id": 0,
            "bbox": [
                1007.3458251953125,
                1263.4600830078125,
                1149.61572265625,
                1422.44287109375
            ],
            "score": 0.7566679120063782
        },
        {
            "category_id": 0,
            "bbox": [
                810.4140014648438,
                764.4710083007812,
                965.9771118164062,
                935.2794189453125
            ],
            "score": 0.7531318068504333
        },
        {
            "category_id": 0,
            "bbox": [
                1099.1317138671875,
                1288.3424072265625,
                1180.08984375,
                1516.7073974609375
            ],
            "score": 0.7498592734336853
        },
        {
            "category_id": 0,
            "bbox": [
                1235.08203125,
                778.1373291015625,
                1302.3521728515625,
                835.9517822265625
            ],
            "score": 0.748827338218689
        },
        {
            "category_id": 0,
            "bbox": [
                1341.0318603515625,
                836.661376953125,
                1404.592041015625,
                904.318115234375
            ],
            "score": 0.7484084963798523
        },
        {
            "category_id": 0,
            "bbox": [
                677.6400756835938,
                1413.2091064453125,
                732.506591796875,
                1504.3077392578125
            ],
            "score": 0.7472715377807617
        },
        {
            "category_id": 0,
            "bbox": [
                2012.1209716796875,
                1444.724853515625,
                2070.555908203125,
                1512.9091796875
            ],
            "score": 0.7469099760055542
        },
        {
            "category_id": 0,
            "bbox": [
                715.1602172851562,
                1451.435546875,
                776.5715942382812,
                1551.0283203125
            ],
            "score": 0.7457225918769836
        },
        {
            "category_id": 0,
            "bbox": [
                1145.643798828125,
                1319.0081787109375,
                1201.1025390625,
                1390.7076416015625
            ],
            "score": 0.7448753118515015
        },
        {
            "category_id": 0,
            "bbox": [
                1560.0968017578125,
                1396.2957763671875,
                1682.1463623046875,
                1550.8519287109375
            ],
            "score": 0.7448103427886963
        },
        {
            "category_id": 0,
            "bbox": [
                276.1582946777344,
                1227.87890625,
                330.1340026855469,
                1301.2877197265625
            ],
            "score": 0.7414299249649048
        },
        {
            "category_id": 0,
            "bbox": [
                1921.8193359375,
                808.0021362304688,
                2140.000244140625,
                1029.7855224609375
            ],
            "score": 0.7404247522354126
        },
        {
            "category_id": 0,
            "bbox": [
                705.3633422851562,
                1668.9781494140625,
                758.303955078125,
                1752.0
            ],
            "score": 0.7398176193237305
        },
        {
            "category_id": 0,
            "bbox": [
                831.992919921875,
                793.9112548828125,
                897.2941284179688,
                994.8473510742188
            ],
            "score": 0.739142894744873
        },
        {
            "category_id": 0,
            "bbox": [
                2059.76806640625,
                1219.945068359375,
                2114.6318359375,
                1315.3760986328125
            ],
            "score": 0.7388283610343933
        },
        {
            "category_id": 0,
            "bbox": [
                489.0999755859375,
                748.8667602539062,
                536.8232421875,
                821.5771484375
            ],
            "score": 0.7380725145339966
        },
        {
            "category_id": 0,
            "bbox": [
                2038.4515380859375,
                1385.5767822265625,
                2098.122802734375,
                1481.1749267578125
            ],
            "score": 0.7372788786888123
        },
        {
            "category_id": 0,
            "bbox": [
                1553.362060546875,
                1512.72607421875,
                1601.466064453125,
                1585.54150390625
            ],
            "score": 0.7330224514007568
        },
        {
            "category_id": 0,
            "bbox": [
                221.14193725585938,
                1163.5966796875,
                300.9771728515625,
                1245.7681884765625
            ],
            "score": 0.7329365015029907
        },
        {
            "category_id": 0,
            "bbox": [
                612.5738525390625,
                1411.419921875,
                672.2621459960938,
                1501.7833251953125
            ],
            "score": 0.7310388684272766
        },
        {
            "category_id": 0,
            "bbox": [
                1343.965576171875,
                760.8369750976562,
                1468.2559814453125,
                945.0670776367188
            ],
            "score": 0.7300430536270142
        },
        {
            "category_id": 0,
            "bbox": [
                1231.42822265625,
                1307.352294921875,
                1312.3936767578125,
                1538.382568359375
            ],
            "score": 0.7299964427947998
        },
        {
            "category_id": 0,
            "bbox": [
                2096.811279296875,
                1054.57421875,
                2200.535400390625,
                1155.0537109375
            ],
            "score": 0.7253382205963135
        },
        {
            "category_id": 0,
            "bbox": [
                1190.892822265625,
                763.361572265625,
                1254.5697021484375,
                834.2601928710938
            ],
            "score": 0.7252641320228577
        },
        {
            "category_id": 0,
            "bbox": [
                1696.2275390625,
                1524.6778564453125,
                1833.432861328125,
                1672.42822265625
            ],
            "score": 0.7237703800201416
        },
        {
            "category_id": 0,
            "bbox": [
                1420.34814453125,
                762.498291015625,
                1567.842041015625,
                924.9199829101562
            ],
            "score": 0.7235816717147827
        },
        {
            "category_id": 0,
            "bbox": [
                1968.45361328125,
                1225.1939697265625,
                2082.180419921875,
                1365.923095703125
            ],
            "score": 0.7235680818557739
        },
        {
            "category_id": 0,
            "bbox": [
                482.27728271484375,
                626.510986328125,
                605.0108642578125,
                787.9507446289062
            ],
            "score": 0.7228288650512695
        },
        {
            "category_id": 0,
            "bbox": [
                1006.152587890625,
                898.0595092773438,
                1134.400146484375,
                1075.2222900390625
            ],
            "score": 0.7227407097816467
        },
        {
            "category_id": 0,
            "bbox": [
                1032.92236328125,
                1292.5650634765625,
                1104.4976806640625,
                1515.6993408203125
            ],
            "score": 0.7226747870445251
        },
        {
            "category_id": 0,
            "bbox": [
                1057.986572265625,
                1006.8712768554688,
                1119.2606201171875,
                1102.073974609375
            ],
            "score": 0.7217151522636414
        },
        {
            "category_id": 0,
            "bbox": [
                1420.7041015625,
                887.6690673828125,
                1490.8424072265625,
                957.3536987304688
            ],
            "score": 0.7215547561645508
        },
        {
            "category_id": 0,
            "bbox": [
                1299.4898681640625,
                649.1113891601562,
                1446.2637939453125,
                796.34814453125
            ],
            "score": 0.7211100459098816
        },
        {
            "category_id": 0,
            "bbox": [
                1929.2686767578125,
                795.75390625,
                2003.777587890625,
                1027.3238525390625
            ],
            "score": 0.7206156849861145
        },
        {
            "category_id": 0,
            "bbox": [
                577.0947875976562,
                733.5072021484375,
                648.8367919921875,
                955.07080078125
            ],
            "score": 0.7198721766471863
        },
        {
            "category_id": 0,
            "bbox": [
                2167.43603515625,
                1010.88671875,
                2223.43701171875,
                1088.227783203125
            ],
            "score": 0.7190478444099426
        },
        {
            "category_id": 0,
            "bbox": [
                1530.306396484375,
                466.1891784667969,
                1587.7943115234375,
                542.94140625
            ],
            "score": 0.7177398204803467
        },
        {
            "category_id": 0,
            "bbox": [
                602.659423828125,
                267.479736328125,
                729.741943359375,
                426.0616149902344
            ],
            "score": 0.7169471979141235
        },
        {
            "category_id": 0,
            "bbox": [
                1248.9715576171875,
                1282.9117431640625,
                1384.9129638671875,
                1431.806640625
            ],
            "score": 0.7168517708778381
        },
        {
            "category_id": 0,
            "bbox": [
                1310.6529541015625,
                678.0381469726562,
                1383.1422119140625,
                742.1513671875
            ],
            "score": 0.7166708707809448
        },
        {
            "category_id": 0,
            "bbox": [
                306.04608154296875,
                634.6830444335938,
                441.4519348144531,
                770.6533813476562
            ],
            "score": 0.7165355682373047
        },
        {
            "category_id": 0,
            "bbox": [
                2126.81005859375,
                1145.26806640625,
                2243.952392578125,
                1284.4073486328125
            ],
            "score": 0.7143636345863342
        },
        {
            "category_id": 0,
            "bbox": [
                2049.73291015625,
                1065.6524658203125,
                2154.9052734375,
                1197.11181640625
            ],
            "score": 0.7138872146606445
        },
        {
            "category_id": 0,
            "bbox": [
                946.3190307617188,
                484.1688537597656,
                1013.2372436523438,
                554.3385009765625
            ],
            "score": 0.7133315801620483
        },
        {
            "category_id": 0,
            "bbox": [
                1178.4322509765625,
                971.64599609375,
                1302.85546875,
                1145.2581787109375
            ],
            "score": 0.7132761478424072
        },
        {
            "category_id": 0,
            "bbox": [
                1077.8428955078125,
                974.9414672851562,
                1144.1812744140625,
                1072.22998046875
            ],
            "score": 0.7128573656082153
        },
        {
            "category_id": 0,
            "bbox": [
                484.4981689453125,
                711.0968017578125,
                621.4969482421875,
                856.377197265625
            ],
            "score": 0.7125664949417114
        },
        {
            "category_id": 0,
            "bbox": [
                177.1964874267578,
                1237.560546875,
                324.9002685546875,
                1388.074951171875
            ],
            "score": 0.7123979926109314
        },
        {
            "category_id": 0,
            "bbox": [
                1841.9698486328125,
                535.40625,
                1894.013427734375,
                609.4550170898438
            ],
            "score": 0.7122899889945984
        },
        {
            "category_id": 0,
            "bbox": [
                1126.2581787109375,
                993.1763916015625,
                1182.67578125,
                1104.0042724609375
            ],
            "score": 0.7116904258728027
        },
        {
            "category_id": 0,
            "bbox": [
                438.8377685546875,
                585.250732421875,
                545.5929565429688,
                730.8687133789062
            ],
            "score": 0.7110756039619446
        },
        {
            "category_id": 0,
            "bbox": [
                1246.5489501953125,
                966.0770874023438,
                1380.774658203125,
                1133.4744873046875
            ],
            "score": 0.7108703255653381
        },
        {
            "category_id": 0,
            "bbox": [
                964.0592041015625,
                805.0553588867188,
                1099.479248046875,
                1000.299072265625
            ],
            "score": 0.7095814347267151
        },
        {
            "category_id": 0,
            "bbox": [
                780.1334838867188,
                1718.5740966796875,
                832.4757080078125,
                1752.0
            ],
            "score": 0.7093410491943359
        },
        {
            "category_id": 0,
            "bbox": [
                897.1632690429688,
                847.7130737304688,
                1006.8568725585938,
                998.2278442382812
            ],
            "score": 0.70929354429245
        },
        {
            "category_id": 0,
            "bbox": [
                540.2791748046875,
                390.4390563964844,
                670.3092041015625,
                524.8615112304688
            ],
            "score": 0.7085620760917664
        },
        {
            "category_id": 0,
            "bbox": [
                844.4269409179688,
                788.09130859375,
                900.9700317382812,
                848.100830078125
            ],
            "score": 0.7084131836891174
        },
        {
            "category_id": 0,
            "bbox": [
                1540.17431640625,
                496.8808898925781,
                1603.3192138671875,
                568.7831420898438
            ],
            "score": 0.708213746547699
        },
        {
            "category_id": 0,
            "bbox": [
                828.1807861328125,
                580.1024169921875,
                894.5750122070312,
                650.9695434570312
            ],
            "score": 0.7081805467605591
        },
        {
            "category_id": 0,
            "bbox": [
                54.70579147338867,
                1210.918212890625,
                178.30810546875,
                1391.4119873046875
            ],
            "score": 0.7078996896743774
        },
        {
            "category_id": 0,
            "bbox": [
                2065.745849609375,
                1464.9373779296875,
                2109.1494140625,
                1570.9854736328125
            ],
            "score": 0.7065691351890564
        },
        {
            "category_id": 0,
            "bbox": [
                1259.7530517578125,
                1315.2193603515625,
                1309.21923828125,
                1393.0557861328125
            ],
            "score": 0.7063839435577393
        },
        {
            "category_id": 0,
            "bbox": [
                1132.859619140625,
                536.710693359375,
                1259.28857421875,
                704.1089477539062
            ],
            "score": 0.7058629989624023
        },
        {
            "category_id": 0,
            "bbox": [
                1306.7059326171875,
                797.139892578125,
                1367.9476318359375,
                872.6862182617188
            ],
            "score": 0.7056727409362793
        },
        {
            "category_id": 0,
            "bbox": [
                261.34765625,
                557.5611572265625,
                331.4702453613281,
                616.2297973632812
            ],
            "score": 0.7056486010551453
        },
        {
            "category_id": 0,
            "bbox": [
                846.8329467773438,
                755.205810546875,
                1086.171875,
                1035.6895751953125
            ],
            "score": 0.7056226134300232
        },
        {
            "category_id": 0,
            "bbox": [
                1540.1580810546875,
                1448.0115966796875,
                1655.4713134765625,
                1601.560791015625
            ],
            "score": 0.7053802013397217
        }
    ]
}